tutorcoursegraph/__about__.py
tutorcoursegraph/__init__.py
tutorcoursegraph/plugin.py
tutorcoursegraph/patches/.gitignore
tutorcoursegraph/patches/caddyfile
tutorcoursegraph/patches/k8s-deployments
tutorcoursegraph/patches/k8s-services
tutorcoursegraph/patches/k8s-volumes
tutorcoursegraph/patches/local-docker-compose-caddy-aliases
tutorcoursegraph/patches/local-docker-compose-dev-services
tutorcoursegraph/patches/local-docker-compose-services
tutorcoursegraph/patches/openedx-cms-common-settings
tutorcoursegraph/templates/coursegraph/apps/.gitignore
tutorcoursegraph/templates/coursegraph/build/.gitignore
tutorcoursegraph/templates/coursegraph/hooks/.gitignore
tutorcoursegraph/templates/coursegraph/hooks/cms/init
tutor_contrib_coursegraph-14.1.0rc4.dist-info/LICENSE.txt
tutor_contrib_coursegraph-14.1.0rc4.dist-info/METADATA
tutor_contrib_coursegraph-14.1.0rc4.dist-info/WHEEL
tutor_contrib_coursegraph-14.1.0rc4.dist-info/entry_points.txt
tutor_contrib_coursegraph-14.1.0rc4.dist-info/top_level.txt
tutor_contrib_coursegraph-14.1.0rc4.dist-info/RECORD
