Metadata-Version: 2.2
Name: tutor-contrib-coursegraph
Version: 14.1.0rc4
Summary: A Tutor plugin that enables the Open edX CourseGraph tool
Home-page: https://github.com/openedx/tutor-contrib-coursegraph
Author: The Center for Reimagining Learning
License: AGPLv3
Project-URL: Code, https://github.com/openedx/tutor-contrib-coursegraph
Project-URL: Issue tracker, https://github.com/openedx/tutor-contrib-coursegraph/issues
Classifier: Development Status :: 4 - Beta
Classifier: Environment :: Console
Classifier: Environment :: Web Environment
Classifier: Intended Audience :: Developers
Classifier: Intended Audience :: Education
Classifier: License :: OSI Approved :: GNU Affero General Public License v3
Classifier: Operating System :: OS Independent
Classifier: Programming Language :: Python
Classifier: Programming Language :: Python :: 3.11
Classifier: Programming Language :: Python :: 3.12
Classifier: Topic :: Education
Classifier: Typing :: Typed
Requires-Python: >=3.11
License-File: LICENSE.txt
Requires-Dist: click
Requires-Dist: tutor<15,>=13.1
Dynamic: author
Dynamic: classifier
Dynamic: description
Dynamic: description-content-type
Dynamic: home-page
Dynamic: license
Dynamic: project-url
Dynamic: requires-dist
Dynamic: requires-python
Dynamic: summary
